{
    "version": 2,
    "targets": [
        {
            "target": "fescar",
            "summarised": [
                {
                    "parameters": {
                        "fuzzing_ratio": 0.0,
                        "class_timeout_sec": 20,
                        "run_timeout_min": 20
                    },
                    "metrics": {
                        "total_classes": 20,
                        "testcases_generated": 530,
                        "classes_failed_to_compile": 0,
                        "classes_canceled_by_timeout": 0,
                        "total_methods": 202,
                        "methods_with_at_least_one_testcase_generated": 169,
                        "methods_with_at_least_one_exception": 8,
                        "methods_without_any_tests_and_exceptions": 31,
                        "total_bytecode_instruction_coverage": 0.4721342621912603,
                        "total_bytecode_instruction_coverage_by_fuzzing": 0.0,
                        "total_bytecode_instruction_coverage_by_concolic": 0.4721342621912603,
                        "averaged_bytecode_instruction_coverage_by_classes": 0.42074680175712914
                    }
                },
                {
                    "parameters": {
                        "fuzzing_ratio": 0.05,
                        "class_timeout_sec": 20,
                        "run_timeout_min": 20
                    },
                    "metrics": {
                        "total_classes": 20,
                        "testcases_generated": 763,
                        "classes_failed_to_compile": 0,
                        "classes_canceled_by_timeout": 0,
                        "total_methods": 202,
                        "methods_with_at_least_one_testcase_generated": 172,
                        "methods_with_at_least_one_exception": 10,
                        "methods_without_any_tests_and_exceptions": 27,
                        "total_bytecode_instruction_coverage": 0.3508009153318078,
                        "total_bytecode_instruction_coverage_by_fuzzing": 0.1940503432494279,
                        "total_bytecode_instruction_coverage_by_concolic": 0.3334096109839817,
                        "averaged_bytecode_instruction_coverage_by_classes": 0.4647797123387707
                    }
                },
                {
                    "parameters": {
                        "fuzzing_ratio": 1.0,
                        "class_timeout_sec": 20,
                        "run_timeout_min": 20
                    },
                    "metrics": {
                        "total_classes": 20,
                        "testcases_generated": 744,
                        "classes_failed_to_compile": 0,
                        "classes_canceled_by_timeout": 19,
                        "total_methods": 202,
                        "methods_with_at_least_one_testcase_generated": 78,
                        "methods_with_at_least_one_exception": 2,
                        "methods_without_any_tests_and_exceptions": 124,
                        "total_bytecode_instruction_coverage": 0.26770538243626063,
                        "total_bytecode_instruction_coverage_by_fuzzing": 0.26770538243626063,
                        "total_bytecode_instruction_coverage_by_concolic": 0.0,
                        "averaged_bytecode_instruction_coverage_by_classes": 0.4193420580041559
                    }
                }
            ],
            "by_class": [
                {
                    "class_name": "com.alibaba.fescar.core.service.ServiceManagerStaticConfigImpl",
                    "data": [
                        {
                            "parameters": {
                                "fuzzing_ratio": 0.0,
                                "class_timeout_sec": 20,
                                "run_timeout_min": 20
                            },
                            "metrics": {
                                "testcases_generated": 2,
                                "failed_to_compile": false,
                                "canceled_by_timeout": false,
                                "total_methods_in_class": 5,
                                "methods_with_at_least_one_testcase_generated": 2,
                                "methods_with_at_least_one_exception": 0,
                                "methods_without_any_tests_and_exceptions": 3,
                                "total_bytecode_instruction_coverage_in_class": 0.0967741935483871,
                                "total_bytecode_instruction_coverage_in_class_by_fuzzing": 0.0,
                                "total_bytecode_instruction_coverage_in_class_by_concolic": 0.0967741935483871
                            }
                        },
                        {
                            "parameters": {
                                "fuzzing_ratio": 0.05,
                                "class_timeout_sec": 20,
                                "run_timeout_min": 20
                            },
                            "metrics": {
                                "testcases_generated": 3,
                                "failed_to_compile": false,
                                "canceled_by_timeout": false,
                                "total_methods_in_class": 5,
                                "methods_with_at_least_one_testcase_generated": 2,
                                "methods_with_at_least_one_exception": 0,
                                "methods_without_any_tests_and_exceptions": 3,
                                "total_bytecode_instruction_coverage_in_class": 0.0967741935483871,
                                "total_bytecode_instruction_coverage_in_class_by_fuzzing": 0.043010752688172046,
                                "total_bytecode_instruction_coverage_in_class_by_concolic": 0.0967741935483871
                            }
                        },
                        {
                            "parameters": {
                                "fuzzing_ratio": 1.0,
                                "class_timeout_sec": 20,
                                "run_timeout_min": 20
                            },
                            "metrics": {
                                "testcases_generated": 1,
                                "failed_to_compile": false,
                                "canceled_by_timeout": true,
                                "total_methods_in_class": 5,
                                "methods_with_at_least_one_testcase_generated": 1,
                                "methods_with_at_least_one_exception": 0,
                                "methods_without_any_tests_and_exceptions": 4,
                                "total_bytecode_instruction_coverage_in_class": 0.043010752688172046,
                                "total_bytecode_instruction_coverage_in_class_by_fuzzing": 0.043010752688172046,
                                "total_bytecode_instruction_coverage_in_class_by_concolic": 0.0
                            }
                        }
                    ]
                },
                {
                    "class_name": "com.alibaba.fescar.core.protocol.MessageFuture",
                    "data": [
                        {
                            "parameters": {
                                "fuzzing_ratio": 0.0,
                                "class_timeout_sec": 20,
                                "run_timeout_min": 20
                            },
                            "metrics": {
                                "testcases_generated": 14,
                                "failed_to_compile": false,
                                "canceled_by_timeout": false,
                                "total_methods_in_class": 8,
                                "methods_with_at_least_one_testcase_generated": 8,
                                "methods_with_at_least_one_exception": 0,
                                "methods_without_any_tests_and_exceptions": 0,
                                "total_bytecode_instruction_coverage_in_class": 0.9166666666666666,
                                "total_bytecode_instruction_coverage_in_class_by_fuzzing": 0.0,
                                "total_bytecode_instruction_coverage_in_class_by_concolic": 0.9166666666666666
                            }
                        },
                        {
                            "parameters": {
                                "fuzzing_ratio": 0.05,
                                "class_timeout_sec": 20,
                                "run_timeout_min": 20
                            },
                            "metrics": {
                                "testcases_generated": 40,
                                "failed_to_compile": false,
                                "canceled_by_timeout": false,
                                "total_methods_in_class": 8,
                                "methods_with_at_least_one_testcase_generated": 8,
                                "methods_with_at_least_one_exception": 1,
                                "methods_without_any_tests_and_exceptions": 0,
                                "total_bytecode_instruction_coverage_in_class": 0.9583333333333334,
                                "total_bytecode_instruction_coverage_in_class_by_fuzzing": 0.75,
                                "total_bytecode_instruction_coverage_in_class_by_concolic": 0.9583333333333334
                            }
                        },
                        {
                            "parameters": {
                                "fuzzing_ratio": 1.0,
                                "class_timeout_sec": 20,
                                "run_timeout_min": 20
                            },
                            "metrics": {
                                "testcases_generated": 35,
                                "failed_to_compile": false,
                                "canceled_by_timeout": true,
                                "total_methods_in_class": 8,
                                "methods_with_at_least_one_testcase_generated": 8,
                                "methods_with_at_least_one_exception": 0,
                                "methods_without_any_tests_and_exceptions": 0,
                                "total_bytecode_instruction_coverage_in_class": 0.7708333333333334,
                                "total_bytecode_instruction_coverage_in_class_by_fuzzing": 0.7708333333333334,
                                "total_bytecode_instruction_coverage_in_class_by_concolic": 0.0
                            }
                        }
                    ]
                },
                {
                    "class_name": "com.alibaba.fescar.core.rpc.netty.TmRpcClient",
                    "data": [
                        {
                            "parameters": {
                                "fuzzing_ratio": 0.0,
                                "class_timeout_sec": 20,
                                "run_timeout_min": 20
                            },
                            "metrics": {
                                "testcases_generated": 26,
                                "failed_to_compile": false,
                                "canceled_by_timeout": false,
                                "total_methods_in_class": 28,
                                "methods_with_at_least_one_testcase_generated": 18,
                                "methods_with_at_least_one_exception": 2,
                                "methods_without_any_tests_and_exceptions": 8,
                                "total_bytecode_instruction_coverage_in_class": 0.0,
                                "total_bytecode_instruction_coverage_in_class_by_fuzzing": 0.0,
                                "total_bytecode_instruction_coverage_in_class_by_concolic": 0.0
                            }
                        },
                        {
                            "parameters": {
                                "fuzzing_ratio": 0.05,
                                "class_timeout_sec": 20,
                                "run_timeout_min": 20
                            },
                            "metrics": {
                                "testcases_generated": 28,
                                "failed_to_compile": false,
                                "canceled_by_timeout": false,
                                "total_methods_in_class": 28,
                                "methods_with_at_least_one_testcase_generated": 18,
                                "methods_with_at_least_one_exception": 3,
                                "methods_without_any_tests_and_exceptions": 7,
                                "total_bytecode_instruction_coverage_in_class": 0.0,
                                "total_bytecode_instruction_coverage_in_class_by_fuzzing": 0.0,
                                "total_bytecode_instruction_coverage_in_class_by_concolic": 0.0
                            }
                        },
                        {
                            "parameters": {
                                "fuzzing_ratio": 1.0,
                                "class_timeout_sec": 20,
                                "run_timeout_min": 20
                            },
                            "metrics": {
                                "testcases_generated": 450,
                                "failed_to_compile": false,
                                "canceled_by_timeout": true,
                                "total_methods_in_class": 28,
                                "methods_with_at_least_one_testcase_generated": 2,
                                "methods_with_at_least_one_exception": 2,
                                "methods_without_any_tests_and_exceptions": 26,
                                "total_bytecode_instruction_coverage_in_class": 0.0,
                                "total_bytecode_instruction_coverage_in_class_by_fuzzing": 0.0,
                                "total_bytecode_instruction_coverage_in_class_by_concolic": 0.0
                            }
                        }
                    ]
                },
                {
                    "class_name": "com.alibaba.fescar.core.rpc.netty.MessageCodecHandler",
                    "data": [
                        {
                            "parameters": {
                                "fuzzing_ratio": 0.0,
                                "class_timeout_sec": 20,
                                "run_timeout_min": 20
                            },
                            "metrics": {
                                "testcases_generated": 59,
                                "failed_to_compile": false,
                                "canceled_by_timeout": false,
                                "total_methods_in_class": 6,
                                "methods_with_at_least_one_testcase_generated": 6,
                                "methods_with_at_least_one_exception": 0,
                                "methods_without_any_tests_and_exceptions": 0,
                                "total_bytecode_instruction_coverage_in_class": 0.29902912621359223,
                                "total_bytecode_instruction_coverage_in_class_by_fuzzing": 0.0,
                                "total_bytecode_instruction_coverage_in_class_by_concolic": 0.29902912621359223
                            }
                        },
                        {
                            "parameters": {
                                "fuzzing_ratio": 0.05,
                                "class_timeout_sec": 20,
                                "run_timeout_min": 20
                            },
                            "metrics": {
                                "testcases_generated": 72,
                                "failed_to_compile": false,
                                "canceled_by_timeout": false,
                                "total_methods_in_class": 6,
                                "methods_with_at_least_one_testcase_generated": 6,
                                "methods_with_at_least_one_exception": 0,
                                "methods_without_any_tests_and_exceptions": 0,
                                "total_bytecode_instruction_coverage_in_class": 0.29902912621359223,
                                "total_bytecode_instruction_coverage_in_class_by_fuzzing": 0.18058252427184465,
                                "total_bytecode_instruction_coverage_in_class_by_concolic": 0.29902912621359223
                            }
                        },
                        {
                            "parameters": {
                                "fuzzing_ratio": 1.0,
                                "class_timeout_sec": 20,
                                "run_timeout_min": 20
                            },
                            "metrics": {
                                "testcases_generated": 12,
                                "failed_to_compile": false,
                                "canceled_by_timeout": true,
                                "total_methods_in_class": 6,
                                "methods_with_at_least_one_testcase_generated": 6,
                                "methods_with_at_least_one_exception": 0,
                                "methods_without_any_tests_and_exceptions": 0,
                                "total_bytecode_instruction_coverage_in_class": 0.18058252427184465,
                                "total_bytecode_instruction_coverage_in_class_by_fuzzing": 0.18058252427184465,
                                "total_bytecode_instruction_coverage_in_class_by_concolic": 0.0
                            }
                        }
                    ]
                },
                {
                    "class_name": "com.alibaba.fescar.core.rpc.netty.NettyPoolableFactory",
                    "data": [
                        {
                            "parameters": {
                                "fuzzing_ratio": 0.0,
                                "class_timeout_sec": 20,
                                "run_timeout_min": 20
                            },
                            "metrics": {
                                "testcases_generated": 56,
                                "failed_to_compile": false,
                                "canceled_by_timeout": false,
                                "total_methods_in_class": 8,
                                "methods_with_at_least_one_testcase_generated": 8,
                                "methods_with_at_least_one_exception": 2,
                                "methods_without_any_tests_and_exceptions": 0,
                                "total_bytecode_instruction_coverage_in_class": 0.3931034482758621,
                                "total_bytecode_instruction_coverage_in_class_by_fuzzing": 0.0,
                                "total_bytecode_instruction_coverage_in_class_by_concolic": 0.3931034482758621
                            }
                        },
                        {
                            "parameters": {
                                "fuzzing_ratio": 0.05,
                                "class_timeout_sec": 20,
                                "run_timeout_min": 20
                            },
                            "metrics": {
                                "testcases_generated": 56,
                                "failed_to_compile": false,
                                "canceled_by_timeout": false,
                                "total_methods_in_class": 8,
                                "methods_with_at_least_one_testcase_generated": 8,
                                "methods_with_at_least_one_exception": 2,
                                "methods_without_any_tests_and_exceptions": 0,
                                "total_bytecode_instruction_coverage_in_class": 0.3758620689655172,
                                "total_bytecode_instruction_coverage_in_class_by_fuzzing": 0.0,
                                "total_bytecode_instruction_coverage_in_class_by_concolic": 0.3758620689655172
                            }
                        },
                        {
                            "parameters": {
                                "fuzzing_ratio": 1.0,
                                "class_timeout_sec": 20,
                                "run_timeout_min": 20
                            },
                            "metrics": {
                                "testcases_generated": 0,
                                "failed_to_compile": false,
                                "canceled_by_timeout": false,
                                "total_methods_in_class": 8,
                                "methods_with_at_least_one_testcase_generated": 0,
                                "methods_with_at_least_one_exception": 0,
                                "methods_without_any_tests_and_exceptions": 8,
                                "total_bytecode_instruction_coverage_in_class": 0.0,
                                "total_bytecode_instruction_coverage_in_class_by_fuzzing": 0.0,
                                "total_bytecode_instruction_coverage_in_class_by_concolic": 0.0
                            }
                        }
                    ]
                },
                {
                    "class_name": "com.alibaba.fescar.core.protocol.transaction.GlobalBeginRequest",
                    "data": [
                        {
                            "parameters": {
                                "fuzzing_ratio": 0.0,
                                "class_timeout_sec": 20,
                                "run_timeout_min": 20
                            },
                            "metrics": {
                                "testcases_generated": 8,
                                "failed_to_compile": false,
                                "canceled_by_timeout": false,
                                "total_methods_in_class": 9,
                                "methods_with_at_least_one_testcase_generated": 7,
                                "methods_with_at_least_one_exception": 0,
                                "methods_without_any_tests_and_exceptions": 2,
                                "total_bytecode_instruction_coverage_in_class": 0.25252525252525254,
                                "total_bytecode_instruction_coverage_in_class_by_fuzzing": 0.0,
                                "total_bytecode_instruction_coverage_in_class_by_concolic": 0.25252525252525254
                            }
                        },
                        {
                            "parameters": {
                                "fuzzing_ratio": 0.05,
                                "class_timeout_sec": 20,
                                "run_timeout_min": 20
                            },
                            "metrics": {
                                "testcases_generated": 18,
                                "failed_to_compile": false,
                                "canceled_by_timeout": false,
                                "total_methods_in_class": 9,
                                "methods_with_at_least_one_testcase_generated": 6,
                                "methods_with_at_least_one_exception": 0,
                                "methods_without_any_tests_and_exceptions": 3,
                                "total_bytecode_instruction_coverage_in_class": 0.23232323232323232,
                                "total_bytecode_instruction_coverage_in_class_by_fuzzing": 0.23232323232323232,
                                "total_bytecode_instruction_coverage_in_class_by_concolic": 0.20202020202020202
                            }
                        },
                        {
                            "parameters": {
                                "fuzzing_ratio": 1.0,
                                "class_timeout_sec": 20,
                                "run_timeout_min": 20
                            },
                            "metrics": {
                                "testcases_generated": 26,
                                "failed_to_compile": false,
                                "canceled_by_timeout": true,
                                "total_methods_in_class": 9,
                                "methods_with_at_least_one_testcase_generated": 9,
                                "methods_with_at_least_one_exception": 0,
                                "methods_without_any_tests_and_exceptions": 0,
                                "total_bytecode_instruction_coverage_in_class": 0.7777777777777778,
                                "total_bytecode_instruction_coverage_in_class_by_fuzzing": 0.7777777777777778,
                                "total_bytecode_instruction_coverage_in_class_by_concolic": 0.0
                            }
                        }
                    ]
                },
                {
                    "class_name": "com.alibaba.fescar.core.model.BranchType",
                    "data": [
                        {
                            "parameters": {
                                "fuzzing_ratio": 0.0,
                                "class_timeout_sec": 20,
                                "run_timeout_min": 20
                            },
                            "metrics": {
                                "testcases_generated": 3,
                                "failed_to_compile": false,
                                "canceled_by_timeout": false,
                                "total_methods_in_class": 2,
                                "methods_with_at_least_one_testcase_generated": 1,
                                "methods_with_at_least_one_exception": 0,
                                "methods_without_any_tests_and_exceptions": 1,
                                "total_bytecode_instruction_coverage_in_class": 0.8113207547169812,
                                "total_bytecode_instruction_coverage_in_class_by_fuzzing": 0.0,
                                "total_bytecode_instruction_coverage_in_class_by_concolic": 0.8113207547169812
                            }
                        },
                        {
                            "parameters": {
                                "fuzzing_ratio": 0.05,
                                "class_timeout_sec": 20,
                                "run_timeout_min": 20
                            },
                            "metrics": {
                                "testcases_generated": 4,
                                "failed_to_compile": false,
                                "canceled_by_timeout": false,
                                "total_methods_in_class": 2,
                                "methods_with_at_least_one_testcase_generated": 1,
                                "methods_with_at_least_one_exception": 0,
                                "methods_without_any_tests_and_exceptions": 1,
                                "total_bytecode_instruction_coverage_in_class": 0.8113207547169812,
                                "total_bytecode_instruction_coverage_in_class_by_fuzzing": 0.7547169811320755,
                                "total_bytecode_instruction_coverage_in_class_by_concolic": 0.8113207547169812
                            }
                        },
                        {
                            "parameters": {
                                "fuzzing_ratio": 1.0,
                                "class_timeout_sec": 20,
                                "run_timeout_min": 20
                            },
                            "metrics": {
                                "testcases_generated": 7,
                                "failed_to_compile": false,
                                "canceled_by_timeout": true,
                                "total_methods_in_class": 2,
                                "methods_with_at_least_one_testcase_generated": 2,
                                "methods_with_at_least_one_exception": 0,
                                "methods_without_any_tests_and_exceptions": 0,
                                "total_bytecode_instruction_coverage_in_class": 0.9056603773584906,
                                "total_bytecode_instruction_coverage_in_class_by_fuzzing": 0.9056603773584906,
                                "total_bytecode_instruction_coverage_in_class_by_concolic": 0.0
                            }
                        }
                    ]
                },
                {
                    "class_name": "com.alibaba.fescar.core.rpc.netty.RpcServerHandler",
                    "data": [
                        {
                            "parameters": {
                                "fuzzing_ratio": 0.0,
                                "class_timeout_sec": 20,
                                "run_timeout_min": 20
                            },
                            "metrics": {
                                "testcases_generated": 45,
                                "failed_to_compile": false,
                                "canceled_by_timeout": false,
                                "total_methods_in_class": 6,
                                "methods_with_at_least_one_testcase_generated": 6,
                                "methods_with_at_least_one_exception": 0,
                                "methods_without_any_tests_and_exceptions": 0,
                                "total_bytecode_instruction_coverage_in_class": 0.4111111111111111,
                                "total_bytecode_instruction_coverage_in_class_by_fuzzing": 0.0,
                                "total_bytecode_instruction_coverage_in_class_by_concolic": 0.4111111111111111
                            }
                        },
                        {
                            "parameters": {
                                "fuzzing_ratio": 0.05,
                                "class_timeout_sec": 20,
                                "run_timeout_min": 20
                            },
                            "metrics": {
                                "testcases_generated": 47,
                                "failed_to_compile": false,
                                "canceled_by_timeout": false,
                                "total_methods_in_class": 6,
                                "methods_with_at_least_one_testcase_generated": 6,
                                "methods_with_at_least_one_exception": 0,
                                "methods_without_any_tests_and_exceptions": 0,
                                "total_bytecode_instruction_coverage_in_class": 0.45555555555555555,
                                "total_bytecode_instruction_coverage_in_class_by_fuzzing": 0.3111111111111111,
                                "total_bytecode_instruction_coverage_in_class_by_concolic": 0.26666666666666666
                            }
                        },
                        {
                            "parameters": {
                                "fuzzing_ratio": 1.0,
                                "class_timeout_sec": 20,
                                "run_timeout_min": 20
                            },
                            "metrics": {
                                "testcases_generated": 7,
                                "failed_to_compile": false,
                                "canceled_by_timeout": true,
                                "total_methods_in_class": 6,
                                "methods_with_at_least_one_testcase_generated": 6,
                                "methods_with_at_least_one_exception": 0,
                                "methods_without_any_tests_and_exceptions": 0,
                                "total_bytecode_instruction_coverage_in_class": 0.3111111111111111,
                                "total_bytecode_instruction_coverage_in_class_by_fuzzing": 0.3111111111111111,
                                "total_bytecode_instruction_coverage_in_class_by_concolic": 0.0
                            }
                        }
                    ]
                },
                {
                    "class_name": "com.alibaba.fescar.core.exception.TransactionExceptionCode",
                    "data": [
                        {
                            "parameters": {
                                "fuzzing_ratio": 0.0,
                                "class_timeout_sec": 20,
                                "run_timeout_min": 20
                            },
                            "metrics": {
                                "testcases_generated": 6,
                                "failed_to_compile": false,
                                "canceled_by_timeout": false,
                                "total_methods_in_class": 2,
                                "methods_with_at_least_one_testcase_generated": 2,
                                "methods_with_at_least_one_exception": 0,
                                "methods_without_any_tests_and_exceptions": 0,
                                "total_bytecode_instruction_coverage_in_class": 0.9056603773584906,
                                "total_bytecode_instruction_coverage_in_class_by_fuzzing": 0.0,
                                "total_bytecode_instruction_coverage_in_class_by_concolic": 0.9056603773584906
                            }
                        },
                        {
                            "parameters": {
                                "fuzzing_ratio": 0.05,
                                "class_timeout_sec": 20,
                                "run_timeout_min": 20
                            },
                            "metrics": {
                                "testcases_generated": 29,
                                "failed_to_compile": false,
                                "canceled_by_timeout": false,
                                "total_methods_in_class": 2,
                                "methods_with_at_least_one_testcase_generated": 2,
                                "methods_with_at_least_one_exception": 0,
                                "methods_without_any_tests_and_exceptions": 0,
                                "total_bytecode_instruction_coverage_in_class": 0.9056603773584906,
                                "total_bytecode_instruction_coverage_in_class_by_fuzzing": 0.9056603773584906,
                                "total_bytecode_instruction_coverage_in_class_by_concolic": 0.8113207547169812
                            }
                        },
                        {
                            "parameters": {
                                "fuzzing_ratio": 1.0,
                                "class_timeout_sec": 20,
                                "run_timeout_min": 20
                            },
                            "metrics": {
                                "testcases_generated": 33,
                                "failed_to_compile": false,
                                "canceled_by_timeout": true,
                                "total_methods_in_class": 2,
                                "methods_with_at_least_one_testcase_generated": 2,
                                "methods_with_at_least_one_exception": 0,
                                "methods_without_any_tests_and_exceptions": 0,
                                "total_bytecode_instruction_coverage_in_class": 0.9056603773584906,
                                "total_bytecode_instruction_coverage_in_class_by_fuzzing": 0.9056603773584906,
                                "total_bytecode_instruction_coverage_in_class_by_concolic": 0.0
                            }
                        }
                    ]
                },
                {
                    "class_name": "com.alibaba.fescar.core.rpc.netty.RpcServer",
                    "data": [
                        {
                            "parameters": {
                                "fuzzing_ratio": 0.0,
                                "class_timeout_sec": 20,
                                "run_timeout_min": 20
                            },
                            "metrics": {
                                "testcases_generated": 47,
                                "failed_to_compile": false,
                                "canceled_by_timeout": false,
                                "total_methods_in_class": 20,
                                "methods_with_at_least_one_testcase_generated": 16,
                                "methods_with_at_least_one_exception": 1,
                                "methods_without_any_tests_and_exceptions": 4,
                                "total_bytecode_instruction_coverage_in_class": 0.23483365949119372,
                                "total_bytecode_instruction_coverage_in_class_by_fuzzing": 0.0,
                                "total_bytecode_instruction_coverage_in_class_by_concolic": 0.23483365949119372
                            }
                        },
                        {
                            "parameters": {
                                "fuzzing_ratio": 0.05,
                                "class_timeout_sec": 20,
                                "run_timeout_min": 20
                            },
                            "metrics": {
                                "testcases_generated": 53,
                                "failed_to_compile": false,
                                "canceled_by_timeout": false,
                                "total_methods_in_class": 20,
                                "methods_with_at_least_one_testcase_generated": 15,
                                "methods_with_at_least_one_exception": 1,
                                "methods_without_any_tests_and_exceptions": 5,
                                "total_bytecode_instruction_coverage_in_class": 0.30332681017612523,
                                "total_bytecode_instruction_coverage_in_class_by_fuzzing": 0.003913894324853229,
                                "total_bytecode_instruction_coverage_in_class_by_concolic": 0.30332681017612523
                            }
                        },
                        {
                            "parameters": {
                                "fuzzing_ratio": 1.0,
                                "class_timeout_sec": 20,
                                "run_timeout_min": 20
                            },
                            "metrics": {
                                "testcases_generated": 1,
                                "failed_to_compile": false,
                                "canceled_by_timeout": true,
                                "total_methods_in_class": 20,
                                "methods_with_at_least_one_testcase_generated": 1,
                                "methods_with_at_least_one_exception": 0,
                                "methods_without_any_tests_and_exceptions": 19,
                                "total_bytecode_instruction_coverage_in_class": 0.003913894324853229,
                                "total_bytecode_instruction_coverage_in_class_by_fuzzing": 0.003913894324853229,
                                "total_bytecode_instruction_coverage_in_class_by_concolic": 0.0
                            }
                        }
                    ]
                },
                {
                    "class_name": "com.alibaba.fescar.core.protocol.transaction.GlobalBeginResponse",
                    "data": [
                        {
                            "parameters": {
                                "fuzzing_ratio": 0.0,
                                "class_timeout_sec": 20,
                                "run_timeout_min": 20
                            },
                            "metrics": {
                                "testcases_generated": 18,
                                "failed_to_compile": false,
                                "canceled_by_timeout": false,
                                "total_methods_in_class": 8,
                                "methods_with_at_least_one_testcase_generated": 8,
                                "methods_with_at_least_one_exception": 1,
                                "methods_without_any_tests_and_exceptions": 0,
                                "total_bytecode_instruction_coverage_in_class": 0.19672131147540983,
                                "total_bytecode_instruction_coverage_in_class_by_fuzzing": 0.0,
                                "total_bytecode_instruction_coverage_in_class_by_concolic": 0.19672131147540983
                            }
                        },
                        {
                            "parameters": {
                                "fuzzing_ratio": 0.05,
                                "class_timeout_sec": 20,
                                "run_timeout_min": 20
                            },
                            "metrics": {
                                "testcases_generated": 20,
                                "failed_to_compile": false,
                                "canceled_by_timeout": false,
                                "total_methods_in_class": 8,
                                "methods_with_at_least_one_testcase_generated": 8,
                                "methods_with_at_least_one_exception": 1,
                                "methods_without_any_tests_and_exceptions": 0,
                                "total_bytecode_instruction_coverage_in_class": 0.2540983606557377,
                                "total_bytecode_instruction_coverage_in_class_by_fuzzing": 0.02459016393442623,
                                "total_bytecode_instruction_coverage_in_class_by_concolic": 0.2540983606557377
                            }
                        },
                        {
                            "parameters": {
                                "fuzzing_ratio": 1.0,
                                "class_timeout_sec": 20,
                                "run_timeout_min": 20
                            },
                            "metrics": {
                                "testcases_generated": 1,
                                "failed_to_compile": false,
                                "canceled_by_timeout": true,
                                "total_methods_in_class": 8,
                                "methods_with_at_least_one_testcase_generated": 1,
                                "methods_with_at_least_one_exception": 0,
                                "methods_without_any_tests_and_exceptions": 7,
                                "total_bytecode_instruction_coverage_in_class": 0.02459016393442623,
                                "total_bytecode_instruction_coverage_in_class_by_fuzzing": 0.02459016393442623,
                                "total_bytecode_instruction_coverage_in_class_by_concolic": 0.0
                            }
                        }
                    ]
                },
                {
                    "class_name": "com.alibaba.fescar.core.protocol.MergeResultMessage",
                    "data": [
                        {
                            "parameters": {
                                "fuzzing_ratio": 0.0,
                                "class_timeout_sec": 20,
                                "run_timeout_min": 20
                            },
                            "metrics": {
                                "testcases_generated": 4,
                                "failed_to_compile": false,
                                "canceled_by_timeout": false,
                                "total_methods_in_class": 8,
                                "methods_with_at_least_one_testcase_generated": 4,
                                "methods_with_at_least_one_exception": 0,
                                "methods_without_any_tests_and_exceptions": 4,
                                "total_bytecode_instruction_coverage_in_class": 0.06091370558375635,
                                "total_bytecode_instruction_coverage_in_class_by_fuzzing": 0.0,
                                "total_bytecode_instruction_coverage_in_class_by_concolic": 0.06091370558375635
                            }
                        },
                        {
                            "parameters": {
                                "fuzzing_ratio": 0.05,
                                "class_timeout_sec": 20,
                                "run_timeout_min": 20
                            },
                            "metrics": {
                                "testcases_generated": 10,
                                "failed_to_compile": false,
                                "canceled_by_timeout": false,
                                "total_methods_in_class": 8,
                                "methods_with_at_least_one_testcase_generated": 4,
                                "methods_with_at_least_one_exception": 0,
                                "methods_without_any_tests_and_exceptions": 4,
                                "total_bytecode_instruction_coverage_in_class": 0.06091370558375635,
                                "total_bytecode_instruction_coverage_in_class_by_fuzzing": 0.06091370558375635,
                                "total_bytecode_instruction_coverage_in_class_by_concolic": 0.06091370558375635
                            }
                        },
                        {
                            "parameters": {
                                "fuzzing_ratio": 1.0,
                                "class_timeout_sec": 20,
                                "run_timeout_min": 20
                            },
                            "metrics": {
                                "testcases_generated": 14,
                                "failed_to_compile": false,
                                "canceled_by_timeout": true,
                                "total_methods_in_class": 8,
                                "methods_with_at_least_one_testcase_generated": 8,
                                "methods_with_at_least_one_exception": 0,
                                "methods_without_any_tests_and_exceptions": 0,
                                "total_bytecode_instruction_coverage_in_class": 0.2436548223350254,
                                "total_bytecode_instruction_coverage_in_class_by_fuzzing": 0.2436548223350254,
                                "total_bytecode_instruction_coverage_in_class_by_concolic": 0.0
                            }
                        }
                    ]
                },
                {
                    "class_name": "com.alibaba.fescar.core.rpc.netty.RmMessageListener",
                    "data": [
                        {
                            "parameters": {
                                "fuzzing_ratio": 0.0,
                                "class_timeout_sec": 20,
                                "run_timeout_min": 20
                            },
                            "metrics": {
                                "testcases_generated": 18,
                                "failed_to_compile": false,
                                "canceled_by_timeout": false,
                                "total_methods_in_class": 5,
                                "methods_with_at_least_one_testcase_generated": 5,
                                "methods_with_at_least_one_exception": 0,
                                "methods_without_any_tests_and_exceptions": 0,
                                "total_bytecode_instruction_coverage_in_class": 0.0,
                                "total_bytecode_instruction_coverage_in_class_by_fuzzing": 0.0,
                                "total_bytecode_instruction_coverage_in_class_by_concolic": 0.0
                            }
                        },
                        {
                            "parameters": {
                                "fuzzing_ratio": 0.05,
                                "class_timeout_sec": 20,
                                "run_timeout_min": 20
                            },
                            "metrics": {
                                "testcases_generated": 26,
                                "failed_to_compile": false,
                                "canceled_by_timeout": false,
                                "total_methods_in_class": 5,
                                "methods_with_at_least_one_testcase_generated": 5,
                                "methods_with_at_least_one_exception": 0,
                                "methods_without_any_tests_and_exceptions": 0,
                                "total_bytecode_instruction_coverage_in_class": 0.47413793103448276,
                                "total_bytecode_instruction_coverage_in_class_by_fuzzing": 0.33620689655172414,
                                "total_bytecode_instruction_coverage_in_class_by_concolic": 0.31896551724137934
                            }
                        },
                        {
                            "parameters": {
                                "fuzzing_ratio": 1.0,
                                "class_timeout_sec": 20,
                                "run_timeout_min": 20
                            },
                            "metrics": {
                                "testcases_generated": 7,
                                "failed_to_compile": false,
                                "canceled_by_timeout": true,
                                "total_methods_in_class": 5,
                                "methods_with_at_least_one_testcase_generated": 4,
                                "methods_with_at_least_one_exception": 0,
                                "methods_without_any_tests_and_exceptions": 1,
                                "total_bytecode_instruction_coverage_in_class": 0.33620689655172414,
                                "total_bytecode_instruction_coverage_in_class_by_fuzzing": 0.33620689655172414,
                                "total_bytecode_instruction_coverage_in_class_by_concolic": 0.0
                            }
                        }
                    ]
                },
                {
                    "class_name": "com.alibaba.fescar.core.rpc.ClientType",
                    "data": [
                        {
                            "parameters": {
                                "fuzzing_ratio": 0.0,
                                "class_timeout_sec": 20,
                                "run_timeout_min": 20
                            },
                            "metrics": {
                                "testcases_generated": 6,
                                "failed_to_compile": false,
                                "canceled_by_timeout": false,
                                "total_methods_in_class": 2,
                                "methods_with_at_least_one_testcase_generated": 2,
                                "methods_with_at_least_one_exception": 0,
                                "methods_without_any_tests_and_exceptions": 0,
                                "total_bytecode_instruction_coverage_in_class": 0.9056603773584906,
                                "total_bytecode_instruction_coverage_in_class_by_fuzzing": 0.0,
                                "total_bytecode_instruction_coverage_in_class_by_concolic": 0.9056603773584906
                            }
                        },
                        {
                            "parameters": {
                                "fuzzing_ratio": 0.05,
                                "class_timeout_sec": 20,
                                "run_timeout_min": 20
                            },
                            "metrics": {
                                "testcases_generated": 12,
                                "failed_to_compile": false,
                                "canceled_by_timeout": false,
                                "total_methods_in_class": 2,
                                "methods_with_at_least_one_testcase_generated": 2,
                                "methods_with_at_least_one_exception": 0,
                                "methods_without_any_tests_and_exceptions": 0,
                                "total_bytecode_instruction_coverage_in_class": 0.9056603773584906,
                                "total_bytecode_instruction_coverage_in_class_by_fuzzing": 0.9056603773584906,
                                "total_bytecode_instruction_coverage_in_class_by_concolic": 0.8113207547169812
                            }
                        },
                        {
                            "parameters": {
                                "fuzzing_ratio": 1.0,
                                "class_timeout_sec": 20,
                                "run_timeout_min": 20
                            },
                            "metrics": {
                                "testcases_generated": 7,
                                "failed_to_compile": false,
                                "canceled_by_timeout": true,
                                "total_methods_in_class": 2,
                                "methods_with_at_least_one_testcase_generated": 2,
                                "methods_with_at_least_one_exception": 0,
                                "methods_without_any_tests_and_exceptions": 0,
                                "total_bytecode_instruction_coverage_in_class": 0.9056603773584906,
                                "total_bytecode_instruction_coverage_in_class_by_fuzzing": 0.9056603773584906,
                                "total_bytecode_instruction_coverage_in_class_by_concolic": 0.0
                            }
                        }
                    ]
                },
                {
                    "class_name": "com.alibaba.fescar.core.protocol.transaction.BranchRegisterRequest",
                    "data": [
                        {
                            "parameters": {
                                "fuzzing_ratio": 0.0,
                                "class_timeout_sec": 20,
                                "run_timeout_min": 20
                            },
                            "metrics": {
                                "testcases_generated": 7,
                                "failed_to_compile": false,
                                "canceled_by_timeout": false,
                                "total_methods_in_class": 13,
                                "methods_with_at_least_one_testcase_generated": 6,
                                "methods_with_at_least_one_exception": 0,
                                "methods_without_any_tests_and_exceptions": 7,
                                "total_bytecode_instruction_coverage_in_class": 0.11917098445595854,
                                "total_bytecode_instruction_coverage_in_class_by_fuzzing": 0.0,
                                "total_bytecode_instruction_coverage_in_class_by_concolic": 0.11917098445595854
                            }
                        },
                        {
                            "parameters": {
                                "fuzzing_ratio": 0.05,
                                "class_timeout_sec": 20,
                                "run_timeout_min": 20
                            },
                            "metrics": {
                                "testcases_generated": 34,
                                "failed_to_compile": false,
                                "canceled_by_timeout": false,
                                "total_methods_in_class": 13,
                                "methods_with_at_least_one_testcase_generated": 11,
                                "methods_with_at_least_one_exception": 0,
                                "methods_without_any_tests_and_exceptions": 2,
                                "total_bytecode_instruction_coverage_in_class": 0.20207253886010362,
                                "total_bytecode_instruction_coverage_in_class_by_fuzzing": 0.20207253886010362,
                                "total_bytecode_instruction_coverage_in_class_by_concolic": 0.19170984455958548
                            }
                        },
                        {
                            "parameters": {
                                "fuzzing_ratio": 1.0,
                                "class_timeout_sec": 20,
                                "run_timeout_min": 20
                            },
                            "metrics": {
                                "testcases_generated": 58,
                                "failed_to_compile": false,
                                "canceled_by_timeout": true,
                                "total_methods_in_class": 13,
                                "methods_with_at_least_one_testcase_generated": 13,
                                "methods_with_at_least_one_exception": 0,
                                "methods_without_any_tests_and_exceptions": 0,
                                "total_bytecode_instruction_coverage_in_class": 0.7253886010362695,
                                "total_bytecode_instruction_coverage_in_class_by_fuzzing": 0.7253886010362695,
                                "total_bytecode_instruction_coverage_in_class_by_concolic": 0.0
                            }
                        }
                    ]
                },
                {
                    "class_name": "com.alibaba.fescar.core.model.GlobalStatus",
                    "data": [
                        {
                            "parameters": {
                                "fuzzing_ratio": 0.0,
                                "class_timeout_sec": 20,
                                "run_timeout_min": 20
                            },
                            "metrics": {
                                "testcases_generated": 3,
                                "failed_to_compile": false,
                                "canceled_by_timeout": false,
                                "total_methods_in_class": 2,
                                "methods_with_at_least_one_testcase_generated": 1,
                                "methods_with_at_least_one_exception": 0,
                                "methods_without_any_tests_and_exceptions": 1,
                                "total_bytecode_instruction_coverage_in_class": 0.8113207547169812,
                                "total_bytecode_instruction_coverage_in_class_by_fuzzing": 0.0,
                                "total_bytecode_instruction_coverage_in_class_by_concolic": 0.8113207547169812
                            }
                        },
                        {
                            "parameters": {
                                "fuzzing_ratio": 0.05,
                                "class_timeout_sec": 20,
                                "run_timeout_min": 20
                            },
                            "metrics": {
                                "testcases_generated": 15,
                                "failed_to_compile": false,
                                "canceled_by_timeout": false,
                                "total_methods_in_class": 2,
                                "methods_with_at_least_one_testcase_generated": 1,
                                "methods_with_at_least_one_exception": 0,
                                "methods_without_any_tests_and_exceptions": 1,
                                "total_bytecode_instruction_coverage_in_class": 0.8113207547169812,
                                "total_bytecode_instruction_coverage_in_class_by_fuzzing": 0.8113207547169812,
                                "total_bytecode_instruction_coverage_in_class_by_concolic": 0.8113207547169812
                            }
                        },
                        {
                            "parameters": {
                                "fuzzing_ratio": 1.0,
                                "class_timeout_sec": 20,
                                "run_timeout_min": 20
                            },
                            "metrics": {
                                "testcases_generated": 33,
                                "failed_to_compile": false,
                                "canceled_by_timeout": true,
                                "total_methods_in_class": 2,
                                "methods_with_at_least_one_testcase_generated": 2,
                                "methods_with_at_least_one_exception": 0,
                                "methods_without_any_tests_and_exceptions": 0,
                                "total_bytecode_instruction_coverage_in_class": 0.9056603773584906,
                                "total_bytecode_instruction_coverage_in_class_by_fuzzing": 0.9056603773584906,
                                "total_bytecode_instruction_coverage_in_class_by_concolic": 0.0
                            }
                        }
                    ]
                },
                {
                    "class_name": "com.alibaba.fescar.core.protocol.ResultCode",
                    "data": [
                        {
                            "parameters": {
                                "fuzzing_ratio": 0.0,
                                "class_timeout_sec": 20,
                                "run_timeout_min": 20
                            },
                            "metrics": {
                                "testcases_generated": 6,
                                "failed_to_compile": false,
                                "canceled_by_timeout": false,
                                "total_methods_in_class": 2,
                                "methods_with_at_least_one_testcase_generated": 2,
                                "methods_with_at_least_one_exception": 0,
                                "methods_without_any_tests_and_exceptions": 0,
                                "total_bytecode_instruction_coverage_in_class": 0.9056603773584906,
                                "total_bytecode_instruction_coverage_in_class_by_fuzzing": 0.0,
                                "total_bytecode_instruction_coverage_in_class_by_concolic": 0.9056603773584906
                            }
                        },
                        {
                            "parameters": {
                                "fuzzing_ratio": 0.05,
                                "class_timeout_sec": 20,
                                "run_timeout_min": 20
                            },
                            "metrics": {
                                "testcases_generated": 12,
                                "failed_to_compile": false,
                                "canceled_by_timeout": false,
                                "total_methods_in_class": 2,
                                "methods_with_at_least_one_testcase_generated": 2,
                                "methods_with_at_least_one_exception": 0,
                                "methods_without_any_tests_and_exceptions": 0,
                                "total_bytecode_instruction_coverage_in_class": 0.9056603773584906,
                                "total_bytecode_instruction_coverage_in_class_by_fuzzing": 0.9056603773584906,
                                "total_bytecode_instruction_coverage_in_class_by_concolic": 0.8113207547169812
                            }
                        },
                        {
                            "parameters": {
                                "fuzzing_ratio": 1.0,
                                "class_timeout_sec": 20,
                                "run_timeout_min": 20
                            },
                            "metrics": {
                                "testcases_generated": 6,
                                "failed_to_compile": false,
                                "canceled_by_timeout": true,
                                "total_methods_in_class": 2,
                                "methods_with_at_least_one_testcase_generated": 2,
                                "methods_with_at_least_one_exception": 0,
                                "methods_without_any_tests_and_exceptions": 0,
                                "total_bytecode_instruction_coverage_in_class": 0.8113207547169812,
                                "total_bytecode_instruction_coverage_in_class_by_fuzzing": 0.8113207547169812,
                                "total_bytecode_instruction_coverage_in_class_by_concolic": 0.0
                            }
                        }
                    ]
                },
                {
                    "class_name": "com.alibaba.fescar.core.rpc.RpcContext",
                    "data": [
                        {
                            "parameters": {
                                "fuzzing_ratio": 0.0,
                                "class_timeout_sec": 20,
                                "run_timeout_min": 20
                            },
                            "metrics": {
                                "testcases_generated": 91,
                                "failed_to_compile": false,
                                "canceled_by_timeout": false,
                                "total_methods_in_class": 27,
                                "methods_with_at_least_one_testcase_generated": 27,
                                "methods_with_at_least_one_exception": 0,
                                "methods_without_any_tests_and_exceptions": 0,
                                "total_bytecode_instruction_coverage_in_class": 0.7718832891246684,
                                "total_bytecode_instruction_coverage_in_class_by_fuzzing": 0.0,
                                "total_bytecode_instruction_coverage_in_class_by_concolic": 0.7718832891246684
                            }
                        },
                        {
                            "parameters": {
                                "fuzzing_ratio": 0.05,
                                "class_timeout_sec": 20,
                                "run_timeout_min": 20
                            },
                            "metrics": {
                                "testcases_generated": 111,
                                "failed_to_compile": false,
                                "canceled_by_timeout": false,
                                "total_methods_in_class": 27,
                                "methods_with_at_least_one_testcase_generated": 27,
                                "methods_with_at_least_one_exception": 0,
                                "methods_without_any_tests_and_exceptions": 0,
                                "total_bytecode_instruction_coverage_in_class": 0.7320954907161804,
                                "total_bytecode_instruction_coverage_in_class_by_fuzzing": 0.5305039787798409,
                                "total_bytecode_instruction_coverage_in_class_by_concolic": 0.6763925729442971
                            }
                        },
                        {
                            "parameters": {
                                "fuzzing_ratio": 1.0,
                                "class_timeout_sec": 20,
                                "run_timeout_min": 20
                            },
                            "metrics": {
                                "testcases_generated": 46,
                                "failed_to_compile": false,
                                "canceled_by_timeout": true,
                                "total_methods_in_class": 27,
                                "methods_with_at_least_one_testcase_generated": 9,
                                "methods_with_at_least_one_exception": 0,
                                "methods_without_any_tests_and_exceptions": 18,
                                "total_bytecode_instruction_coverage_in_class": 0.5358090185676393,
                                "total_bytecode_instruction_coverage_in_class_by_fuzzing": 0.5358090185676393,
                                "total_bytecode_instruction_coverage_in_class_by_concolic": 0.0
                            }
                        }
                    ]
                },
                {
                    "class_name": "com.alibaba.fescar.core.rpc.netty.RmRpcClient",
                    "data": [
                        {
                            "parameters": {
                                "fuzzing_ratio": 0.0,
                                "class_timeout_sec": 20,
                                "run_timeout_min": 20
                            },
                            "metrics": {
                                "testcases_generated": 57,
                                "failed_to_compile": false,
                                "canceled_by_timeout": false,
                                "total_methods_in_class": 31,
                                "methods_with_at_least_one_testcase_generated": 30,
                                "methods_with_at_least_one_exception": 1,
                                "methods_without_any_tests_and_exceptions": 1,
                                "total_bytecode_instruction_coverage_in_class": 0.0,
                                "total_bytecode_instruction_coverage_in_class_by_fuzzing": 0.0,
                                "total_bytecode_instruction_coverage_in_class_by_concolic": 0.0
                            }
                        },
                        {
                            "parameters": {
                                "fuzzing_ratio": 0.05,
                                "class_timeout_sec": 20,
                                "run_timeout_min": 20
                            },
                            "metrics": {
                                "testcases_generated": 62,
                                "failed_to_compile": false,
                                "canceled_by_timeout": false,
                                "total_methods_in_class": 31,
                                "methods_with_at_least_one_testcase_generated": 30,
                                "methods_with_at_least_one_exception": 1,
                                "methods_without_any_tests_and_exceptions": 1,
                                "total_bytecode_instruction_coverage_in_class": 0.18886861313868614,
                                "total_bytecode_instruction_coverage_in_class_by_fuzzing": 0.01551094890510949,
                                "total_bytecode_instruction_coverage_in_class_by_concolic": 0.18886861313868614
                            }
                        },
                        {
                            "parameters": {
                                "fuzzing_ratio": 1.0,
                                "class_timeout_sec": 20,
                                "run_timeout_min": 20
                            },
                            "metrics": {
                                "testcases_generated": 0,
                                "failed_to_compile": false,
                                "canceled_by_timeout": true,
                                "total_methods_in_class": 31,
                                "methods_with_at_least_one_testcase_generated": 0,
                                "methods_with_at_least_one_exception": 0,
                                "methods_without_any_tests_and_exceptions": 31,
                                "total_bytecode_instruction_coverage_in_class": 0.0,
                                "total_bytecode_instruction_coverage_in_class_by_fuzzing": 0.0,
                                "total_bytecode_instruction_coverage_in_class_by_concolic": 0.0
                            }
                        }
                    ]
                },
                {
                    "class_name": "com.alibaba.fescar.core.rpc.DefaultServerMessageListenerImpl",
                    "data": [
                        {
                            "parameters": {
                                "fuzzing_ratio": 0.0,
                                "class_timeout_sec": 20,
                                "run_timeout_min": 20
                            },
                            "metrics": {
                                "testcases_generated": 54,
                                "failed_to_compile": false,
                                "canceled_by_timeout": false,
                                "total_methods_in_class": 10,
                                "methods_with_at_least_one_testcase_generated": 10,
                                "methods_with_at_least_one_exception": 1,
                                "methods_without_any_tests_and_exceptions": 0,
                                "total_bytecode_instruction_coverage_in_class": 0.3225806451612903,
                                "total_bytecode_instruction_coverage_in_class_by_fuzzing": 0.0,
                                "total_bytecode_instruction_coverage_in_class_by_concolic": 0.3225806451612903
                            }
                        },
                        {
                            "parameters": {
                                "fuzzing_ratio": 0.05,
                                "class_timeout_sec": 20,
                                "run_timeout_min": 20
                            },
                            "metrics": {
                                "testcases_generated": 111,
                                "failed_to_compile": false,
                                "canceled_by_timeout": false,
                                "total_methods_in_class": 10,
                                "methods_with_at_least_one_testcase_generated": 10,
                                "methods_with_at_least_one_exception": 1,
                                "methods_without_any_tests_and_exceptions": 0,
                                "total_bytecode_instruction_coverage_in_class": 0.3225806451612903,
                                "total_bytecode_instruction_coverage_in_class_by_fuzzing": 0.2870967741935484,
                                "total_bytecode_instruction_coverage_in_class_by_concolic": 0.3225806451612903
                            }
                        },
                        {
                            "parameters": {
                                "fuzzing_ratio": 1.0,
                                "class_timeout_sec": 20,
                                "run_timeout_min": 20
                            },
                            "metrics": {
                                "testcases_generated": 0,
                                "failed_to_compile": false,
                                "canceled_by_timeout": true,
                                "total_methods_in_class": 10,
                                "methods_with_at_least_one_testcase_generated": 0,
                                "methods_with_at_least_one_exception": 0,
                                "methods_without_any_tests_and_exceptions": 10,
                                "total_bytecode_instruction_coverage_in_class": 0.0,
                                "total_bytecode_instruction_coverage_in_class_by_fuzzing": 0.0,
                                "total_bytecode_instruction_coverage_in_class_by_concolic": 0.0
                            }
                        }
                    ]
                }
            ]
        }
    ],
    "metadata": {
        "source": {
            "type": "github-action",
            "id": "6319817970-1"
        },
        "commit_hash": "d514a7b42a7473d72a3c0a6516b79f81f0a2c60d",
        "branch": "main",
        "build_number": "2023.9",
        "timestamp": 1695776228,
        "date": "2023-09-27T00:57:08",
        "environment": {
            "host": "2054af91d353",
            "OS": "Linux version #54~20.04.1-Ubuntu SMP Wed Sep 6 17:49:31 UTC 2023",
            "java_version": "openjdk version \"17.0.6\" 2023-01-17 LTS\nOpenJDK Runtime Environment Zulu17.40+19-CA (build 17.0.6+10-LTS)\nOpenJDK 64-Bit Server VM Zulu17.40+19-CA (build 17.0.6+10-LTS, mixed mode, sharing)\n",
            "gradle_version": "Gradle 7.6.1",
            "JAVA_HOME": "/usr/lib/jvm/zulu17-ca-amd64",
            "KOTLIN_HOME": "/opt/kotlin/kotlinc",
            "PATH": "/__t/Python/3.9.18/x64/bin:/__t/Python/3.9.18/x64:/opt/gradle/gradle-7.6.1/bin:/opt/kotlin/kotlinc/bin:/usr/local/sbin:/usr/local/bin:/usr/sbin:/usr/bin:/sbin:/bin"
        }
    }
}